.coveragerc
.gitignore
.isort.cfg
.pre-commit-config.yaml
AUTHORS.rst
CHANGELOG.rst
LICENSE.txt
README.md
requirements.txt
setup.cfg
setup.py
docs/Makefile
docs/authors.rst
docs/changelog.rst
docs/conf.py
docs/index.rst
docs/license.rst
docs/_static/.gitignore
src/garnn/__init__.py
src/garnn/utils.py
src/garnn.egg-info/PKG-INFO
src/garnn.egg-info/SOURCES.txt
src/garnn.egg-info/dependency_links.txt
src/garnn.egg-info/not-zip-safe
src/garnn.egg-info/requires.txt
src/garnn.egg-info/top_level.txt
src/garnn/components/__init__.py
src/garnn/components/attention.py
src/garnn/components/garnn_gru.py
src/garnn/layers/__init__.py
src/garnn/layers/diffconv.py
src/garnn/layers/gat.py
src/garnn/layers/utils.py
src/garnn/models/__init__.py
src/garnn/models/garnn.py
tests/conftest.py
tests/test_skeleton.py