Metadata-Version: 2.1
Name: garnn
Version: 1.0.3
Summary: TensorFlow implementation of the Graphical Attention Recurrent Neural Net Model
Home-page: https://github.com/LeviBorodenko/garnn
Author: Levi Borodenko
Author-email: Levi.borodenko@gmail.com
License: mit
Platform: any
Classifier: Development Status :: 4 - Beta
Classifier: Programming Language :: Python
Provides-Extra: testing
